MANIFEST.in
Makefile
README.rst
setup.py
docs/HISTORY.txt
src/collective/__init__.py
src/collective.addthis.egg-info/PKG-INFO
src/collective.addthis.egg-info/SOURCES.txt
src/collective.addthis.egg-info/dependency_links.txt
src/collective.addthis.egg-info/entry_points.txt
src/collective.addthis.egg-info/namespace_packages.txt
src/collective.addthis.egg-info/not-zip-safe
src/collective.addthis.egg-info/requires.txt
src/collective.addthis.egg-info/top_level.txt
src/collective/addthis/__init__.py
src/collective/addthis/addthis.pt
src/collective/addthis/addthis.py
src/collective/addthis/configure.zcml
src/collective/addthis/controlpanel.py
src/collective/addthis/interfaces.py
src/collective/addthis/social_media.py
src/collective/addthis/testing.py
src/collective/addthis/upgrades.zcml
src/collective/addthis/Extensions/Install.py
src/collective/addthis/locales/collective.addthis.pot
src/collective/addthis/locales/es/LC_MESSAGES/collective.addthis.po
src/collective/addthis/locales/fi/LC_MESSAGES/collective.addthis.po
src/collective/addthis/locales/fr/LC_MESSAGES/collective.addthis.po
src/collective/addthis/locales/it/LC_MESSAGES/collective.addthis.po
src/collective/addthis/profiles/default/browserlayer.xml
src/collective/addthis/profiles/default/controlpanel.xml
src/collective/addthis/profiles/default/cssregistry.xml
src/collective/addthis/profiles/default/jsregistry.xml
src/collective/addthis/profiles/default/metadata.xml
src/collective/addthis/profiles/default/registry.xml
src/collective/addthis/profiles/upgrades/1000_to_1001/browserlayer.xml
src/collective/addthis/profiles/upgrades/1000_to_1001/controlpanel.xml
src/collective/addthis/profiles/upgrades/1000_to_1001/jsregistry.xml
src/collective/addthis/profiles/upgrades/1000_to_1001/metadata.xml
src/collective/addthis/profiles/upgrades/1000_to_1001/registry.xml
src/collective/addthis/static/addthis.css
src/collective/addthis/static/addthis.gif
src/collective/addthis/static/addthis.js
src/collective/addthis/tests/__init__.py
src/collective/addthis/tests/test_addthis.py
src/collective/addthis/tests/test_controlpanel.py
src/collective/addthis/tests/test_setup.py
src/collective/addthis/upgrades/__init__.py
src/collective/addthis/upgrades/all_to_1000.py
src/collective/addthis/upgrades/v1x.py