Metadata-Version: 1.1
Name: collective.addthis
Version: 1.3.3
Summary: AddThis addon for Plone CMS
Home-page: https://github.com/collective/collective.addthis
Author: Jukka Ojaniemi
Author-email: jukka.ojaniemi@jyu.fi
License: GPL
Keywords: AddThis
Platform: UNKNOWN
Classifier: Framework :: Plone :: 4.1
Classifier: Framework :: Plone :: 4.2
Classifier: Framework :: Plone :: 4.3
Classifier: Programming Language :: Python
Classifier: Topic :: Software Development :: Libraries :: Python Modules
